bjsfm/__init__.py
bjsfm/__main__.py
bjsfm/analysis.py
bjsfm/lekhnitskii.py
bjsfm/plotting.py
bjsfm/utilities.py
bjsfm-0.5.2.dist-info/LICENSE
bjsfm-0.5.2.dist-info/METADATA
bjsfm-0.5.2.dist-info/WHEEL
bjsfm-0.5.2.dist-info/entry_points.txt
bjsfm-0.5.2.dist-info/top_level.txt
bjsfm-0.5.2.dist-info/RECORD
