Metadata-Version: 2.1
Name: bjsfm
Version: 0.5.2
Summary: Bolted Joint Stress Field Model
Home-page: https://github.com/BenjaminETaylor/bjsfm
Author: Benjamin E. Taylor
Author-email: benjaminearltaylor@gmail.com
License: MIT
Keywords: bolted joints stress engineering composites
Classifier: Development Status :: 4 - Beta
Classifier: Intended Audience :: Developers
Classifier: Intended Audience :: Science/Research
Classifier: License :: OSI Approved :: MIT License
Classifier: Programming Language :: Python :: 3
Classifier: Programming Language :: Python :: 3.9
Classifier: Topic :: Scientific/Engineering
Requires-Python: ~=3.9
License-File: LICENSE
Requires-Dist: numpy
Requires-Dist: matplotlib
Requires-Dist: nptyping
